aap_client/__init__.py
aap_client/crypto_files.py
aap_client/tokens.py
aap_client/flask/__init__.py
aap_client/flask/client.py
aap_client/flask/config.py
aap_client/flask/decorators.py
aap_client/flask/exceptions.py
aap_client_python-0.1.4.dist-info/DESCRIPTION.rst
aap_client_python-0.1.4.dist-info/METADATA
aap_client_python-0.1.4.dist-info/RECORD
aap_client_python-0.1.4.dist-info/WHEEL
aap_client_python-0.1.4.dist-info/metadata.json
aap_client_python-0.1.4.dist-info/top_level.txt
