Metadata-Version: 2.0
Name: aap-client-python
Version: 0.1.4
Summary: AAP Client
Home-page: https://github.com/EMBL-EBI-TSI/aap-client-python
Author: Pau Ruiz Safont
Author-email: psafont@ebi.ac.uk
License: Apache 2.0
Keywords: aap jose jwt auth flask
Platform: UNKNOWN
Classifier: Development Status :: 4 - Beta
Classifier: Intended Audience :: Developers
Classifier: License :: OSI Approved :: Apache Software License
Classifier: Programming Language :: Python :: 2
Classifier: Programming Language :: Python :: 2.7
Classifier: Programming Language :: Python :: 3
Classifier: Programming Language :: Python :: 3.4
Classifier: Programming Language :: Python :: 3.5
Classifier: Programming Language :: Python :: 3.6
Requires-Python: >=2.7, !=3.0.*, !=3.1.*, !=3.2.*, !=3.3.*, <4
Provides-Extra: test
Provides-Extra: flask
Provides-Extra: dev
Requires-Dist: future (>=0.16.0)
Requires-Dist: pyjwt[crypto] (>=1.5.2)
Provides-Extra: dev
Requires-Dist: flask (>=0.12.2); extra == 'dev'
Provides-Extra: flask
Requires-Dist: flask (>=0.12.2); extra == 'flask'
Provides-Extra: test
Requires-Dist: flask (>=0.12.2); extra == 'test'
Requires-Dist: pytest; extra == 'test'
Requires-Dist: python-testdata-tsi (>=0.2.0.1); extra == 'test'
Requires-Dist: unittest2; extra == 'test'
